LayerSustainabilityAnalysis/__init__.py
LayerSustainabilityAnalysis/layersustainabilityanalysis.py
LayersSustainabilityAnalysis-1.0.4.dist-info/LICENSE
LayersSustainabilityAnalysis-1.0.4.dist-info/METADATA
LayersSustainabilityAnalysis-1.0.4.dist-info/WHEEL
LayersSustainabilityAnalysis-1.0.4.dist-info/top_level.txt
LayersSustainabilityAnalysis-1.0.4.dist-info/RECORD
