Metadata-Version: 2.1
Name: LayersSustainabilityAnalysis
Version: 1.0.4
Summary: A Python library that analyzes the layer sustainability of neural networks
Home-page: https://github.com/khalooei/LSA
Author: Mohammad Khalooei
License: MIT
Project-URL: Changelog, https://github.com/khalooei/LSA/README.md
Project-URL: Docs, https://github.com/khalooei/LSA/README.md
Platform: UNKNOWN
Classifier: License :: OSI Approved :: MIT License
Classifier: Operating System :: OS Independent
Classifier: Programming Language :: Python
Classifier: Programming Language :: Python :: 3.6
Classifier: Programming Language :: Python :: 3.7
Classifier: Programming Language :: Python :: 3.8
Classifier: Programming Language :: Python :: Implementation :: CPython
Classifier: Programming Language :: Python :: Implementation :: PyPy
License-File: LICENSE
Requires-Dist: torch
Requires-Dist: torchvision
Requires-Dist: matplotlib
